professional_python_exercises_2_githubcli/__init__.py
professional_python_exercises_2_githubcli/github_cli.py
professional_python_exercises_2_githubcli/test_github_cli.py
professional_python_exercises_2_githubcli-0.1.0a0.dist-info/LICENSE
professional_python_exercises_2_githubcli-0.1.0a0.dist-info/WHEEL
professional_python_exercises_2_githubcli-0.1.0a0.dist-info/METADATA
professional_python_exercises_2_githubcli-0.1.0a0.dist-info/RECORD
